README.md
setup.py
jupyter_math/__init__.py
jupyter_math/main.py
jupyter_math.egg-info/PKG-INFO
jupyter_math.egg-info/SOURCES.txt
jupyter_math.egg-info/dependency_links.txt
jupyter_math.egg-info/requires.txt
jupyter_math.egg-info/top_level.txt