Metadata-Version: 2.1
Name: jupyter-math
Version: 0.0.4
Summary: display and evaluate math on jupyter notebook
Home-page: https://github.com/Madoshakalaka/jupyter-math
Author: Matt Yan
Author-email: syan4@ualberta.ca
License: UNKNOWN
Project-URL: Bug Reports, https://github.com/Madoshakalaka/jupyter-math/issues
Project-URL: Funding, https://github.com/Madoshakalaka/jupyter-math
Project-URL: Say Thanks!, https://github.com/Madoshakalaka/jupyter-math
Project-URL: Source, https://github.com/Madoshakalaka/jupyter-math
Platform: UNKNOWN
Classifier: Development Status :: 3 - Alpha
Classifier: Intended Audience :: Developers
Classifier: Topic :: Software Development :: Build Tools
Classifier: License :: OSI Approved :: MIT License
Classifier: Programming Language :: Python :: 3.6
Classifier: Programming Language :: Python :: 3.7
Requires-Python: >3.4, !=3.5.*,  <3.8
